{
  "config": {
    "payoff_type": "BarrierOptionPayoff",
    "n_samples": 5000,
    "n_paths_per_sample": 1000,
    "n_steps": 252,
    "n_trials": 20,
    "use_log_target": true
  },
  "training": {
    "metrics": {
      "rmse": 0.7783305048480316,
      "mae": 0.47709006415956573,
      "r2": 0.9920580849650604
    },
    "optuna": {
      "best_value": 1.4505073584631394,
      "best_params": {
        "n_estimators": 2588,
        "learning_rate": 0.0055902540699806725,
        "num_leaves": 423,
        "min_child_samples": 71,
        "subsample": 0.6557471668089462,
        "colsample_bytree": 0.8817931188036888
      }
    },
    "feature_importance": [
      {
        "feature": "option_type",
        "importance": 216833.3413176969
      },
      {
        "feature": "S0",
        "importance": 109840.61702092682
      },
      {
        "feature": "K",
        "importance": 102210.72814796974
      },
      {
        "feature": "sigma",
        "importance": 63159.738972578896
      },
      {
        "feature": "barrier_frac",
        "importance": 58463.14860746848
      },
      {
        "feature": "T",
        "importance": 15403.889196863776
      },
      {
        "feature": "r",
        "importance": 2707.165461058583
      }
    ]
  },
  "evaluation": {
    "test_cases": [
      {
        "S0": 100.0,
        "r": 0.03,
        "sigma": 0.2,
        "T": 1.0,
        "K": 100.0,
        "barrier_frac": 0.8,
        "option_type": 1.0
      },
      {
        "S0": 100.0,
        "r": 0.02,
        "sigma": 0.25,
        "T": 1.5,
        "K": 95.0,
        "barrier_frac": 0.75,
        "option_type": 0.0
      }
    ],
    "results": [
      {
        "params": {
          "S0": 100.0,
          "r": 0.03,
          "sigma": 0.2,
          "T": 1.0,
          "K": 100.0,
          "barrier_frac": 0.8,
          "option_type": 1.0
        },
        "per_npaths": {
          "500": {
            "MC": {
              "price": 9.373945886362243,
              "std": 13.824391354512844,
              "time": 0.005763053894042969,
              "n_paths": 500
            },
            "Model": {
              "price": 8.233250037052906,
              "time": 0.0019998550415039062,
              "abs_error": 1.1406958493093367,
              "rel_error": 0.12168790636703875,
              "speedup": 2.8817358130662853
            }
          },
          "2000": {
            "MC": {
              "price": 9.115718651732529,
              "std": 13.696625107821422,
              "time": 0.028136014938354492,
              "n_paths": 2000
            },
            "Model": {
              "price": 8.233250037052906,
              "time": 0.0019998550415039062,
              "abs_error": 0.8824686146796221,
              "rel_error": 0.09680735533801282,
              "speedup": 14.069027181688126
            }
          },
          "8000": {
            "MC": {
              "price": 9.026403898958964,
              "std": 13.704788523832665,
              "time": 0.09087443351745605,
              "n_paths": 8000
            },
            "Model": {
              "price": 8.233250037052906,
              "time": 0.0019998550415039062,
              "abs_error": 0.7931538619060579,
              "rel_error": 0.08787041559236387,
              "speedup": 45.440510252742015
            }
          }
        }
      },
      {
        "params": {
          "S0": 100.0,
          "r": 0.02,
          "sigma": 0.25,
          "T": 1.5,
          "K": 95.0,
          "barrier_frac": 0.75,
          "option_type": 0.0
        },
        "per_npaths": {
          "500": {
            "MC": {
              "price": 0.8899812777184123,
              "std": 2.8917749784094826,
              "time": 0.005504608154296875,
              "n_paths": 500
            },
            "Model": {
              "price": 0.9318615341536649,
              "time": 0.0015070438385009766,
              "abs_error": 0.041880256435252616,
              "rel_error": 0.047057457818234484,
              "speedup": 3.6525866160417655
            }
          },
          "2000": {
            "MC": {
              "price": 0.9578655074482233,
              "std": 3.0115303261378124,
              "time": 0.026096582412719727,
              "n_paths": 2000
            },
            "Model": {
              "price": 0.9318615341536649,
              "time": 0.0015070438385009766,
              "abs_error": 0.02600397329455839,
              "rel_error": 0.027147833482211507,
              "speedup": 17.31640563202025
            }
          },
          "8000": {
            "MC": {
              "price": 1.0352709088950176,
              "std": 3.1512653765704344,
              "time": 0.09473490715026855,
              "n_paths": 8000
            },
            "Model": {
              "price": 0.9318615341536649,
              "time": 0.0015070438385009766,
              "abs_error": 0.1034093747413527,
              "rel_error": 0.09988629435335462,
              "speedup": 62.861414333175134
            }
          }
        }
      }
    ],
    "summary": {
      "n_test_cases": 2,
      "errors_by_npaths": {
        "500": {
          "abs_mean": 0.5912880528722946,
          "abs_std": 0.5494077964370421,
          "rel_mean": 0.08437268209263661,
          "rel_std": 0.037315224274402134
        },
        "2000": {
          "abs_mean": 0.45423629398709026,
          "abs_std": 0.42823232069253186,
          "rel_mean": 0.06197759441011216,
          "rel_std": 0.03482976092790066
        },
        "8000": {
          "abs_mean": 0.4482816183237053,
          "abs_std": 0.3448722435823526,
          "rel_mean": 0.09387835497285925,
          "rel_std": 0.006007939380495375
        }
      },
      "times_by_npaths": {
        "500": {
          "mc_mean": 0.005633831024169922,
          "model_mean": 0.0017534494400024414
        },
        "2000": {
          "mc_mean": 0.02711629867553711,
          "model_mean": 0.0017534494400024414
        },
        "8000": {
          "mc_mean": 0.0928046703338623,
          "model_mean": 0.0017534494400024414
        }
      },
      "speedups_by_npaths": {
        "500": {
          "mean": 3.2671612145540254,
          "std": 0.38542540148774007
        },
        "2000": {
          "mean": 15.692716406854188,
          "std": 1.6236892251660615
        },
        "8000": {
          "mean": 54.150962292958575,
          "std": 8.710452040216559
        }
      }
    }
  },
  "timing": {
    "total_seconds": 81.19822597503662
  }
}